constance/__init__.py
constance/_version.py
constance/admin.py
constance/apps.py
constance/base.py
constance/checks.py
constance/codecs.py
constance/context_processors.py
constance/forms.py
constance/models.py
constance/settings.py
constance/signals.py
constance/utils.py
constance/backends/__init__.py
constance/backends/database.py
constance/backends/memory.py
constance/backends/redisd.py
constance/locale/ar/LC_MESSAGES/django.mo
constance/locale/ar/LC_MESSAGES/django.po
constance/locale/cs_CZ/LC_MESSAGES/django.mo
constance/locale/cs_CZ/LC_MESSAGES/django.po
constance/locale/de/LC_MESSAGES/django.mo
constance/locale/de/LC_MESSAGES/django.po
constance/locale/en/LC_MESSAGES/django.mo
constance/locale/en/LC_MESSAGES/django.po
constance/locale/es/LC_MESSAGES/django.mo
constance/locale/es/LC_MESSAGES/django.po
constance/locale/et/LC_MESSAGES/django.mo
constance/locale/et/LC_MESSAGES/django.po
constance/locale/fa/LC_MESSAGES/django.mo
constance/locale/fa/LC_MESSAGES/django.po
constance/locale/fr/LC_MESSAGES/django.mo
constance/locale/fr/LC_MESSAGES/django.po
constance/locale/it/LC_MESSAGES/django.mo
constance/locale/it/LC_MESSAGES/django.po
constance/locale/pl/LC_MESSAGES/django.mo
constance/locale/pl/LC_MESSAGES/django.po
constance/locale/ru/LC_MESSAGES/django.mo
constance/locale/ru/LC_MESSAGES/django.po
constance/locale/tr/LC_MESSAGES/django.mo
constance/locale/tr/LC_MESSAGES/django.po
constance/locale/uk/LC_MESSAGES/django.mo
constance/locale/uk/LC_MESSAGES/django.po
constance/locale/zh_CN/LC_MESSAGES/django.mo
constance/locale/zh_CN/LC_MESSAGES/django.po
constance/locale/zh_Hans/LC_MESSAGES/django.mo
constance/locale/zh_Hans/LC_MESSAGES/django.po
constance/management/__init__.py
constance/management/commands/__init__.py
constance/management/commands/constance.py
constance/migrations/0001_initial.py
constance/migrations/0002_migrate_from_old_table.py
constance/migrations/0003_drop_pickle.py
constance/migrations/__init__.py
constance/static/admin/css/constance.css
django_constance-4.3.3.dist-info/METADATA
django_constance-4.3.3.dist-info/WHEEL
django_constance-4.3.3.dist-info/entry_points.txt
django_constance-4.3.3.dist-info/top_level.txt
django_constance-4.3.3.dist-info/RECORD
