Metadata-Version: 2.4
Name: django-constance
Version: 4.3.3
Summary: Django live settings with pluggable backends, including Redis.
Author-email: Jannis Leidel <jannis@leidel.info>
License: BSD
Project-URL: homepage, https://github.com/jazzband/django-constance/
Project-URL: documentation, https://django-constance.readthedocs.io/en/latest/
Project-URL: repository, https://github.com/jazzband/django-constance/
Project-URL: changelog, https://github.com/jazzband/django-constance/releases/
Keywords: django,libraries,redis,settings
Classifier: Development Status :: 5 - Production/Stable
Classifier: Environment :: Web Environment
Classifier: Framework :: Django
Classifier: Framework :: Django :: 4.2
Classifier: Framework :: Django :: 5.0
Classifier: Framework :: Django :: 5.1
Classifier: Framework :: Django :: 5.2
Classifier: Intended Audience :: Developers
Classifier: License :: OSI Approved :: BSD License
Classifier: Natural Language :: English
Classifier: Operating System :: OS Independent
Classifier: Programming Language :: Python
Classifier: Programming Language :: Python :: 3
Classifier: Programming Language :: Python :: 3 :: Only
Classifier: Programming Language :: Python :: 3.8
Classifier: Programming Language :: Python :: 3.9
Classifier: Programming Language :: Python :: 3.10
Classifier: Programming Language :: Python :: 3.11
Classifier: Programming Language :: Python :: 3.12
Classifier: Programming Language :: Python :: 3.13
Classifier: Programming Language :: Python :: Implementation :: CPython
Classifier: Topic :: Utilities
Requires-Python: >=3.8
Provides-Extra: redis
Requires-Dist: redis; extra == "redis"
